persian_payment_gateway/__init__.py
persian_payment_gateway/base.py
persian_payment_gateway/zarinpal.py
persian_payment_gateway-1.0.2.dist-info/LICENSE.txt
persian_payment_gateway-1.0.2.dist-info/METADATA
persian_payment_gateway-1.0.2.dist-info/WHEEL
persian_payment_gateway-1.0.2.dist-info/top_level.txt
persian_payment_gateway-1.0.2.dist-info/RECORD
