Metadata-Version: 2.1
Name: persian_payment_gateway
Version: 1.0.2
Summary: A package to manage multiple payment gateways
Home-page: https://github.com/yourusername/payment_gateway_package
Author: Abbas Rahimzadeh
Author-email: arahimzadeh@gmail.com
Classifier: Programming Language :: Python :: 3
Classifier: License :: OSI Approved :: MIT License
Classifier: Operating System :: OS Independent
License-File: LICENSE.txt
Requires-Dist: requests
